perceptra/__init__.py
perceptra/config.py
perceptra/version.py
perceptra/cli/__init__.py
perceptra/cli/commands.py
perceptra/core/__init__.py
perceptra/core/calibration.py
perceptra/core/classifier.py
perceptra/core/confidence.py
perceptra/core/embeddings/__init__.py
perceptra/core/embeddings/base.py
perceptra/core/embeddings/clip.py
perceptra/core/embeddings/dinov2.py
perceptra/core/embeddings/meta_perception.py
perceptra/core/embeddings/perception.py
perceptra/core/vector_store/__init__.py
perceptra/core/vector_store/base.py
perceptra/core/vector_store/faiss_store.py
perceptra/core/vector_store/qdrant_store.py
perceptra/service/__init__.py
perceptra/service/app.py
perceptra/service/middleware.py
perceptra/service/models.py
perceptra/service/routes/__init__.py
perceptra/service/routes/calibration.py
perceptra/service/routes/classification.py
perceptra/service/routes/health.py
perceptra/utils/__init__.py
perceptra/utils/image.py
perceptra/utils/logging.py
perceptra/utils/metrics.py
perceptra-0.2.1.dist-info/licenses/LICENSE
perceptra-0.2.1.dist-info/METADATA
perceptra-0.2.1.dist-info/WHEEL
perceptra-0.2.1.dist-info/entry_points.txt
perceptra-0.2.1.dist-info/top_level.txt
perceptra-0.2.1.dist-info/RECORD
