Metadata-Version: 2.4
Name: perceptra
Version: 0.2.1
Summary: Production-ready  object classification via vector retrieval
Author-email: Tannous Geagea <tannousgeagea@hotmail.com>
License: MIT
Keywords: computer-vision,detection,vector-search,embedding
Requires-Python: >=3.9
License-File: LICENSE
Requires-Dist: numpy>=1.24.0
Requires-Dist: pillow>=10.0.0
Requires-Dist: pydantic>=2.0.0
Requires-Dist: pydantic-settings>=2.0.0
Requires-Dist: pyyaml>=6.0
Requires-Dist: fastapi>=0.104.0
Requires-Dist: uvicorn[standard]>=0.24.0
Requires-Dist: python-multipart>=0.0.6
Requires-Dist: aiofiles>=23.0.0
Requires-Dist: httpx>=0.25.0
Requires-Dist: click>=8.1.0
Requires-Dist: rich>=13.0.0
Requires-Dist: python-dotenv>=1.0.0
Requires-Dist: prometheus-client>=0.19.0
Provides-Extra: clip
Requires-Dist: torch>=2.0.0; extra == "clip"
Requires-Dist: torchvision>=0.15.0; extra == "clip"
Requires-Dist: open_clip_torch>=2.20.0; extra == "clip"
Provides-Extra: faiss
Requires-Dist: faiss-cpu>=1.7.4; extra == "faiss"
Provides-Extra: qdrant
Requires-Dist: qdrant-client>=1.7.0; extra == "qdrant"
Provides-Extra: dev
Requires-Dist: pytest>=7.4.0; extra == "dev"
Requires-Dist: pytest-cov>=4.1.0; extra == "dev"
Requires-Dist: pytest-asyncio>=0.21.0; extra == "dev"
Requires-Dist: black>=23.0.0; extra == "dev"
Requires-Dist: ruff>=0.1.0; extra == "dev"
Requires-Dist: mypy>=1.7.0; extra == "dev"
Requires-Dist: pre-commit>=3.5.0; extra == "dev"
Provides-Extra: all
Requires-Dist: perceptra[clip,dev,faiss,qdrant]; extra == "all"
Dynamic: license-file
Dynamic: requires-python
